Metadata-Version: 2.1
Name: Skyforce
Version: 0.1.0
Summary: Skyforce provides stable implementations of various Python functions.
Home-page: UNKNOWN
Author: Aaron Ma
License: MIT
Keywords: python,skyforce
Platform: UNKNOWN
Classifier: License :: OSI Approved :: MIT License
